eptlsoot2/__init__.py
eptlsoot2/_eptlsoot2.cp311-win32.pyd
eptlsoot2/cpfr.py
eptlsoot2/eptlsoot2.py
eptlsoot2/psr.py
eptlsoot2/sootgas.py
eptlsoot2-0.0.2.dist-info/METADATA
eptlsoot2-0.0.2.dist-info/WHEEL
eptlsoot2-0.0.2.dist-info/top_level.txt
eptlsoot2-0.0.2.dist-info/RECORD
